clickhouse_migrate/__init__.py
clickhouse_migrate/manage.py
clickhouse_migrate/validation.py
clickhouse_migrate/common/__init__.py
clickhouse_migrate/common/db.py
clickhouse_migrate/common/meta.py
clickhouse_migrate/common/exceptions/__init__.py
clickhouse_migrate/common/exceptions/config.py
clickhouse_migrate/common/models/__init__.py
clickhouse_migrate/common/models/base.py
clickhouse_migrate/common/models/db.py
clickhouse_migrate/conf/__init__.py
clickhouse_migrate/conf/settings.py
clickhouse_migrate/interfaces/__init__.py
clickhouse_migrate/interfaces/repo.py
clickhouse_migrate/interfaces/service.py
clickhouse_migrate/models/__init__.py
clickhouse_migrate/models/migration.py
clickhouse_migrate-0.0.4.dist-info/LICENSE
clickhouse_migrate-0.0.4.dist-info/METADATA
clickhouse_migrate-0.0.4.dist-info/WHEEL
clickhouse_migrate-0.0.4.dist-info/entry_points.txt
clickhouse_migrate-0.0.4.dist-info/top_level.txt
clickhouse_migrate-0.0.4.dist-info/RECORD
