Metadata-Version: 2.1
Name: clickhouse-migrate
Version: 0.0.4
Summary: Migration library for Clickhouse
Author-email: Pavel Trunov <xpen95@gmail.com>
License: MIT License        
Project-URL: homepage, https://github.com/trushad0w/clickhouse-migrate
Project-URL: documentation, https://github.com/trushad0w/clickhouse-migrate
Project-URL: repository, https://github.com/trushad0w/clickhouse-migrate
Keywords: clickhouse,databases,migrations,data science
Classifier: Development Status :: 4 - Beta
Classifier: Environment :: Console
Classifier: Intended Audience :: Developers
Classifier: Intended Audience :: Information Technology
Classifier: License :: OSI Approved :: MIT License
Classifier: Operating System :: OS Independent
Classifier: Programming Language :: SQL
Classifier: Programming Language :: Python :: 3.7
Classifier: Programming Language :: Python :: 3.8
Classifier: Programming Language :: Python :: 3.9
Classifier: Programming Language :: Python :: 3.10
Classifier: Programming Language :: Python :: Implementation :: PyPy
Classifier: Topic :: Database
Classifier: Topic :: Software Development
Classifier: Topic :: Software Development :: Libraries
Classifier: Topic :: Software Development :: Libraries :: Python Modules
Classifier: Topic :: Scientific/Engineering :: Information Analysis
Requires-Python: >=3.7
License-File: LICENSE
Requires-Dist: click (>=8.0.3)
Requires-Dist: clickhouse-driver (>=0.2.2)
Requires-Dist: envparse (==0.2.0)
Requires-Dist: importlib-metadata ; python_version >= "3.7"
Provides-Extra: dev
Requires-Dist: isort (==5.10.1) ; extra == 'dev'
Requires-Dist: black (==22.3.0) ; extra == 'dev'
Requires-Dist: pre-commit (>=2.17.0) ; extra == 'dev'
Requires-Dist: flake8 (==4.0.1) ; extra == 'dev'
Provides-Extra: tests
Requires-Dist: pytest (==6.2.5) ; extra == 'tests'
Requires-Dist: pytest-mock (==3.6.1) ; extra == 'tests'
Requires-Dist: pytest-cov (==3.0.0) ; extra == 'tests'
